{"cameraMode":{"drawMode":0,"name":"Shaded","section":"Shading Mode"},"sceneLighting":true,"audioPlay":false,"sceneViewState":{"m_AlwaysRefresh":false,"showFog":true,"showSkybox":true,"showFlares":true,"showImageEffects":true,"showParticleSystems":true,"showVisualEffectGraphs":true,"m_FxEnabled":true},"in2DMode":false,"pivot":{"x":-93.54166412353516,"y":-4.210258483886719,"z":110.55953979492188},"rotation":{"x":-0.2059004008769989,"y":0.11332021653652191,"z":-0.024012451991438867,"w":-0.9716938734054565},"size":2.2103431224823,"orthographic":false}